{
    "arch": null,
    "build": "pyhd8ed1ab_0",
    "build_number": 0,
    "channel": "https://conda.anaconda.org/conda-forge",
    "depends": [
        "python >=3.10"
    ],
    "fn": "charset-normalizer-3.4.4-pyhd8ed1ab_0.conda",
    "license": "MIT",
    "license_family": "MIT",
    "md5": "a22d1fd9bf98827e280a02875d9a007a",
    "name": "charset-normalizer",
    "noarch": "python",
    "platform": null,
    "sha256": "b32f8362e885f1b8417bac2b3da4db7323faa12d5db62b7fd6691c02d60d6f59",
    "size": 50965,
    "subdir": "noarch",
    "timestamp": 1760437331772,
    "url": "https://conda.anaconda.org/conda-forge/noarch/charset-normalizer-3.4.4-pyhd8ed1ab_0.conda",
    "version": "3.4.4"
}